bjt/__init__.py
bjt/bjt.py
carriers/__init__.py
carriers/carrier_extension.py
carriers/carrier_transport.py
carriers/density_states.py
carriers/dist_functions.py
carriers/equilibrium_density.py
carriers/microscopic_transport.py
characterization/__init__.py
characterization/cv_measurements.py
constants/__init__.py
constants/constants.py
diodes/__init__.py
diodes/diode.py
fets/__init__.py
fets/finfet.py
fets/jfet.py
fets/mesfet.py
fets/mosfet.py
heterostructures/__init__.py
heterostructures/heterostructure.py
interfaces/__init__.py
interfaces/schottky.py
materials/__init__.py
materials/alas.py
materials/algaas.py
materials/algaassb.py
materials/algan.py
materials/algasb.py
materials/aln.py
materials/alp.py
materials/alsb.py
materials/bn.py
materials/cdmnte.py
materials/cds.py
materials/cdse.py
materials/cdte.py
materials/gaas.py
materials/gaasp.py
materials/gaassb.py
materials/gainas.py
materials/gainasp.py
materials/gainassb.py
materials/gainn.py
materials/gainsb.py
materials/gan.py
materials/gap.py
materials/gasb.py
materials/ge.py
materials/hgcdte.py
materials/hgs.py
materials/inalas.py
materials/inas.py
materials/inassb.py
materials/inn.py
materials/inp.py
materials/insb.py
materials/mgo.py
materials/pbs.py
materials/pbse.py
materials/pbte.py
materials/semiconductor.py
materials/si.py
materials/sic.py
materials/sige.py
materials/zno.py
materials/zns.py
materials/znse.py
materials/znte.py
math/__init__.py
math/coordinate.py
math/functions.py
optoelectronic/__init__.py
plot/__init__.py
plot/plots.py
quantum/__init__.py
quantum/quantum.py
structure/__init__.py
structure/bandstructure.py
structure/dynamics.py
semicpy-0.0.2.dist-info/LICENSE
semicpy-0.0.2.dist-info/METADATA
semicpy-0.0.2.dist-info/WHEEL
semicpy-0.0.2.dist-info/top_level.txt
semicpy-0.0.2.dist-info/RECORD
