Metadata-Version: 2.1
Name: semicpy
Version: 0.0.2
Summary: Semiconductor physics calculation and modeling
Home-page: https://github.com/nkskumar/semic
Author: Nithin Kumar Santha Kumar
Author-email: nxs169230@utdallas.edu
Project-URL: Bug Tracker, https://github.com/nkskumar/semic/issues
Classifier: Programming Language :: Python :: 3
Classifier: License :: OSI Approved :: MIT License
Classifier: Operating System :: OS Independent
Requires-Python: >=3.0
License-File: LICENSE
